interface_expander/CtrlInterface.py
interface_expander/DigitalToAnalog.py
interface_expander/EchoCom.py
interface_expander/I2cInterface.py
interface_expander/InterfaceExpander.py
interface_expander/Memory.py
interface_expander/Singleton.py
interface_expander/__init__.py
interface_expander/tiny_frame.py
interface_expander/tf/LICENSE
interface_expander/tf/PayloadBuilder.py
interface_expander/tf/PayloadParser.py
interface_expander/tf/README.md
interface_expander/tf/TinyFrame.py
interface_expander/tf/__init__.py
interface_expander-1.0.4.dist-info/licenses/LICENSE.md
interface_expander-1.0.4.dist-info/METADATA
interface_expander-1.0.4.dist-info/WHEEL
interface_expander-1.0.4.dist-info/top_level.txt
interface_expander-1.0.4.dist-info/RECORD
