Metadata-Version: 2.4
Name: interface-expander
Version: 1.0.4
Summary: A Python library for controlling the Interface Expander device
Author-email: AlmCoding <your.email@example.com>
License: # LICENSE
Project-URL: Homepage, https://www.tindie.com/stores/almcoding/
Project-URL: Repository, https://github.com/AlmCoding/expander-py
License-File: LICENSE.md
Requires-Dist: pyserial>=3.5
Requires-Dist: protobuf==5.29.4
Dynamic: license-file
